repopacker/__init__.py
repopacker/add.py
repopacker/clean.py
repopacker/commands.py
repopacker/config.py
repopacker/constants.py
repopacker/download.py
repopacker/git.py
repopacker/init_cmd.py
repopacker/list_cmd.py
repopacker/main.py
repopacker/pack.py
repopacker/remove.py
repopacker/types.py
repopacker/unpack.py
repopacker/utils.py
repopacker-0.2.1.dist-info/LICENSE
repopacker-0.2.1.dist-info/METADATA
repopacker-0.2.1.dist-info/WHEEL
repopacker-0.2.1.dist-info/entry_points.txt
repopacker-0.2.1.dist-info/RECORD
