Metadata-Version: 2.1
Name: repopacker
Version: 0.2.1
Summary: A low-tech solution to large files in Git
License: GPL-3.0-or-later
Author: Kevin Course
Author-email: kevin.course@mail.utoronto.ca
Requires-Python: >=3.10,<4.0
Classifier: License :: OSI Approved :: GNU General Public License v3 or later (GPLv3+)
Classifier: Programming Language :: Python :: 3
Classifier: Programming Language :: Python :: 3.10
Classifier: Programming Language :: Python :: 3.11
Classifier: Programming Language :: Python :: 3.12
Requires-Dist: requests (>=2.31.0,<3.0.0)
